server.py
iflow_mcp_braindead_dev_instagram_dms_mcp-0.1.4.dist-info/METADATA
iflow_mcp_braindead_dev_instagram_dms_mcp-0.1.4.dist-info/WHEEL
iflow_mcp_braindead_dev_instagram_dms_mcp-0.1.4.dist-info/entry_points.txt
iflow_mcp_braindead_dev_instagram_dms_mcp-0.1.4.dist-info/top_level.txt
iflow_mcp_braindead_dev_instagram_dms_mcp-0.1.4.dist-info/RECORD
