Metadata-Version: 2.4
Name: iflow-mcp_braindead-dev_instagram-dms-mcp
Version: 0.1.4
Summary: A Model Context Protocol server that lets AI assistants read and send Instagram DMs
Requires-Python: >=3.11
Requires-Dist: fastmcp>=2.12.0
Requires-Dist: uvicorn>=0.35.0
Requires-Dist: httpx
Requires-Dist: python-dotenv
